README.md
setup.cfg
setup.py
conan_ldap/__init__.py
conan_ldap/ldap_authentication.py
conan_ldap/requirements.txt
conan_ldap/requirements_test.txt
conan_ldap/test/__init__.py
conan_ldap/test/configuration_file.py
conan_ldap/test/test_authentication.py
conan_ldap/test/test_conan_authentication.py
conan_ldap_authentication.egg-info/PKG-INFO
conan_ldap_authentication.egg-info/SOURCES.txt
conan_ldap_authentication.egg-info/dependency_links.txt
conan_ldap_authentication.egg-info/requires.txt
conan_ldap_authentication.egg-info/top_level.txt