Metadata-Version: 1.1
Name: conan-ldap-authentication
Version: 0.4.1
Summary: LDAP authenticator for Conan C/C++ package manager
Home-page: https://github.com/uilianries/conan-ldap-authentication
Author: Uilian Ries
Author-email: uilianries@gmail.com
License: MIT
Keywords: conan,ldap,package,authentication
Platform: UNKNOWN
Classifier: Development Status :: 5 - Production/Stable
Classifier: Intended Audience :: Developers
Classifier: Topic :: Software Development :: Build Tools
Classifier: License :: OSI Approved :: MIT License
Classifier: Programming Language :: Python :: 2
Classifier: Programming Language :: Python :: 2.7
Classifier: Programming Language :: Python :: 3
